configtype/__init__.py
configtype/errors.py
configtype/jsonconfig.py
configtype/test/__init__.py
configtype/test/test_json.py
configtype-0.0.8.dist-info/LICENCE.txt
configtype-0.0.8.dist-info/METADATA
configtype-0.0.8.dist-info/WHEEL
configtype-0.0.8.dist-info/namespace_packages.txt
configtype-0.0.8.dist-info/top_level.txt
configtype-0.0.8.dist-info/RECORD
