Metadata-Version: 2.1
Name: configtype
Version: 0.0.8
Summary: Configtype bridges json configuration to python.
Home-page: https://github.com/specialunderwear/configtype
Author: Lars van de Kerkhof
Author-email: lars@permanentmarkers.nl
License: GPLv3
Platform: UNKNOWN
Requires-Dist: setuptools
Requires-Dist: six
Provides-Extra: test
Requires-Dist: nose ; extra == 'test'
